loggle/__init__.py
loggle/collections/__init__.py
loggle/configuration/__init__.py
loggle/configuration/configuration.py
loggle/filter/__init__.py
loggle/filter/collections/__init__.py
loggle/filter/collections/filters.py
loggle/filter/error_filter.py
loggle/filter/lib/__init__.py
loggle/filter/lib/consts.py
loggle/filter/lib/schemas.py
loggle/formatter/__init__.py
loggle/formatter/collections/__init__.py
loggle/formatter/collections/formatters.py
loggle/formatter/json_formatter.py
loggle/formatter/lib/__init__.py
loggle/formatter/lib/consts.py
loggle/formatter/lib/schemas.py
loggle/formatter/standard_formatter.py
loggle/handler/__init__.py
loggle/handler/collections/__init__.py
loggle/handler/collections/handler_classes.py
loggle/handler/json_file_handler.py
loggle/handler/lib/__init__.py
loggle/handler/lib/consts.py
loggle/handler/lib/schemas.py
loggle/handler/lib/types.py
loggle/handler/lib/utils.py
loggle/handler/queue_handler.py
loggle/lib/__init__.py
loggle/lib/factory.py
loggle/log/__init__.py
loggle/log/lib/__init__.py
loggle/log/lib/consts.py
loggle/log/lib/schemas.py
loggle/log/log.py
loggle/logger/__init__.py
loggle/logger/collections/__init__.py
loggle/logger/collections/logger_names.py
loggle/logger/lib/__init__.py
loggle/logger/lib/consts.py
loggle/logger/lib/schemas.py
loggle/logger/logger.py
loggle-0.1.2.dist-info/METADATA
loggle-0.1.2.dist-info/WHEEL
loggle-0.1.2.dist-info/RECORD
