Metadata-Version: 2.3
Name: loggle
Version: 0.1.2
Summary: Type-safe, customizable logging configuration for Python
License: MIT
Keywords: logging,type-safety,uvicorn
Author: Kieran Lock
Author-email: kieran.lock@outlook.com
Requires-Python: >=3.13,<4.0
Classifier: License :: OSI Approved :: MIT License
Classifier: Programming Language :: Python :: 3
Classifier: Programming Language :: Python :: 3.13
Requires-Dist: dill (>=0.3.9,<0.4.0)
Requires-Dist: pydantic (>=2.9.2,<3.0.0)
Project-URL: Documentation, https://github.com/Kieran-Lock/loggle/
Project-URL: Homepage, https://github.com/Kieran-Lock/loggle/
Project-URL: Repository, https://github.com/Kieran-Lock/loggle/
